MANIFEST.in
sale_crm_data.xml
sale_crm_view.xml
setup.py
./__init__.py
./__openerp__.py
./sale_crm.py
./report/__init__.py
./report/sales_crm_account_invoice_report.py
./wizard/__init__.py
./wizard/crm_make_sale.py
i18n/ar.po
i18n/bg.po
i18n/bs.po
i18n/ca.po
i18n/cs.po
i18n/da.po
i18n/de.po
i18n/el.po
i18n/es.po
i18n/es_AR.po
i18n/es_CL.po
i18n/es_CR.po
i18n/es_MX.po
i18n/es_VE.po
i18n/et.po
i18n/fi.po
i18n/fr.po
i18n/gl.po
i18n/he.po
i18n/hr.po
i18n/hu.po
i18n/id.po
i18n/it.po
i18n/ja.po
i18n/ko.po
i18n/lt.po
i18n/lv.po
i18n/mk.po
i18n/mn.po
i18n/nb.po
i18n/nl.po
i18n/nl_BE.po
i18n/pl.po
i18n/pt.po
i18n/pt_BR.po
i18n/ro.po
i18n/ru.po
i18n/sale_crm.pot
i18n/sk.po
i18n/sl.po
i18n/sq.po
i18n/sv.po
i18n/tlh.po
i18n/tr.po
i18n/uk.po
i18n/vi.po
i18n/zh_CN.po
i18n/zh_TW.po
images/crm_statistics_dashboard.jpeg
images/opportunity_to_quote.jpeg
openerp_sale_crm.egg-info/PKG-INFO
openerp_sale_crm.egg-info/SOURCES.txt
openerp_sale_crm.egg-info/dependency_links.txt
openerp_sale_crm.egg-info/requires.txt
openerp_sale_crm.egg-info/top_level.txt
process/sale_crm_process.xml
report/sale_crm_account_invoice_report_view.xml
security/ir.model.access.csv
security/sale_crm_security.xml
test/sale_crm.yml
wizard/crm_make_sale_view.xml